docusearch/__init__.py
docusearch/app.py
docusearch-0.5.0.dist-info/LICENSE
docusearch-0.5.0.dist-info/METADATA
docusearch-0.5.0.dist-info/WHEEL
docusearch-0.5.0.dist-info/entry_points.txt
docusearch-0.5.0.dist-info/top_level.txt
docusearch-0.5.0.dist-info/RECORD
